add_package/Add.py
add_package/__init__.py
add_package/dir_file.py
add_package/paddle_test.py
add_package-2.2.3.dist-info/LICENSE
add_package-2.2.3.dist-info/METADATA
add_package-2.2.3.dist-info/WHEEL
add_package-2.2.3.dist-info/top_level.txt
add_package-2.2.3.dist-info/RECORD
