Metadata-Version: 2.1
Name: add-package
Version: 2.2.3
Summary: A method of benchmark
Home-page: https://github.com/pypa/sampleproject
Author: xiaoyang
Author-email: yangx9810@163.com
License: UNKNOWN
Platform: UNKNOWN
Classifier: Programming Language :: Python :: 3
Classifier: License :: OSI Approved :: MIT License
Classifier: Operating System :: OS Independent
License-File: LICENSE
